
FIND test1
    aload_1
    iload_0
    iaload
    ireturn
====
    iload_0
    aload_1
    swap
    iaload
    ireturn
END

FIND test2
    aload_0
    iconst_2|bipush 2|sipush 2|ldc 2
    iaload
    invokestatic Method A_read3 test1 [(]I[)]I
====
    iconst_2|bipush 2|sipush 2|ldc 2
    aload_0
    swap
    iaload
    invokestatic Method A_read3 test1 [(]I[)]I
END

FIND test3
    aload_1
    iload_0
    invokestatic Method A_read3 test1 [(]I[)]I,faload
====
    iload_0
    aload_1
    swap
    invokestatic Method A_read3 test1 [(]I[)]I,faload
END
